<?xml version="1.0"?>
<PropertyList>
    <path>beecha35int.ac</path>

    <effect>
        <inherits-from>Models/Effects/bonanza-reflect</inherits-from>
        <object-name>chromecenter</object-name>
        <object-name>yokeport</object-name>
        <object-name>centerpiece</object-name>
        <object-name>pbuttontrim</object-name>
    </effect>

    <model>
        <name>vsi</name>
        <path>Aircraft/Instruments-3d/vsi/vsi.xml</path>
        <offsets>
            <x-m>2.02548</x-m>
            <y-m>.0563244</y-m>
            <z-m>.352056</z-m>
        </offsets>
    </model>

    <model>
        <name>turnbank</name>
        <path>Models/Instruments/turn/turn.xml</path>
        <offsets>
            <x-m>2.02548</x-m>
            <y-m>-.0563244</y-m>
            <z-m>.352056</z-m>
        </offsets>
    </model>

    <model>
        <name>ai</name>
        <path>Models/Instruments/ai/ai.xml</path>
        <offsets>
            <x-m>2.02548</x-m>
            <y-m>-.1612911</y-m>
            <z-m>.3278169</z-m>
        </offsets>
    </model>

    <model>
        <name>man</name>
        <path>Models/Instruments/man/man.xml</path>
        <offsets>
            <x-m>2.02548</x-m>
            <y-m>.1612911</y-m>
            <z-m>.3278169</z-m>
        </offsets>
    </model>

    <model>
        <name>tac</name>
        <path>Models/Instruments/tachometer/tachometer.xml</path>
        <offsets>
            <x-m>2.02548</x-m>
            <y-m>.2610878</y-m>
            <z-m>.3278169</z-m>
        </offsets>
    </model>

    <model>
        <name>asi</name>
        <path>Models/Instruments/asi/asi.xml</path>
        <offsets>
            <x-m>2.02548</x-m>
            <y-m>-.2610878</y-m>
            <z-m>.3278169</z-m>
        </offsets>
    </model>
    
</PropertyList>